{
"type": "FeatureCollection",
"name": "notable_sites",
"features": [
{ "type": "Feature", "properties": { "id": 3, "name": "parking", "features": "you can park for free here" }, "geometry": { "type": "Point", "coordinates": [ -84.241894290422181, 37.553959350269395 ] } },
{ "type": "Feature", "properties": { "id": 2, "name": "Restrooms", "features": "facilities for useing the bathroom" }, "geometry": { "type": "Point", "coordinates": [ -84.240494296768347, 37.554010527422584 ] } },
{ "type": "Feature", "properties": { "id": 3, "name": "walking_sticks", "features": "walking sticks are availible here" }, "geometry": { "type": "Point", "coordinates": [ -84.238538351617947, 37.555755287881333 ] } }
]
}
